jaydebeapi_hsqldb/__init__.py
jaydebeapi_hsqldb-0.0.3.dist-info/COPYING
jaydebeapi_hsqldb-0.0.3.dist-info/COPYING.LESSER
jaydebeapi_hsqldb-0.0.3.dist-info/METADATA
jaydebeapi_hsqldb-0.0.3.dist-info/WHEEL
jaydebeapi_hsqldb-0.0.3.dist-info/top_level.txt
jaydebeapi_hsqldb-0.0.3.dist-info/RECORD
