Metadata-Version: 2.2
Name: jaydebeapi-hsqldb
Version: 0.0.3
Summary: A module for connecting to HyperSQL using JDBC, based on JayDeBeApi
Home-page: https://github.com/pebble94464/jaydebeapi-hsqldb
Author: Pebble94464
Author-email: jaydebeapi-hsqldb@pebble.plus.com
License: MIT License
Keywords: hypersql hsqldb jdbc
Classifier: Development Status :: 4 - Beta
Classifier: Intended Audience :: Developers
Classifier: License :: OSI Approved :: MIT License
Classifier: Programming Language :: Python
Classifier: Programming Language :: Python :: 3
Classifier: Topic :: Database
Classifier: Topic :: Software Development :: Libraries :: Python Modules
License-File: COPYING
License-File: COPYING.LESSER
Requires-Dist: JPype1; python_version > "2.7" and platform_python_implementation != "Jython"
Requires-Dist: JPype1<=0.7.1; python_version <= "2.7" and platform_python_implementation != "Jython"
Dynamic: author
Dynamic: author-email
Dynamic: classifier
Dynamic: description
Dynamic: description-content-type
Dynamic: home-page
Dynamic: keywords
Dynamic: license
Dynamic: requires-dist
Dynamic: summary
